{
  "quests": [
    {
      "id": "quest-delivery-001",
      "name": "Доставка груза",
      "description": "Офицер NCPD Сара Миллер просит доставить посылку из Downtown в Watson торговцу Рита Морено. Это простое задание для новичков, но нужно быть осторожным при перемещении между районами.",
      "type": "side",
      "giverNpcId": "npc-sarah-miller",
      "level": 1,
      "objectives": [
        {
          "id": "obj-accept-quest",
          "description": "Принять квест от Сары Миллер",
          "type": "npc",
          "target": {
            "type": "npc",
            "id": "npc-sarah-miller"
          },
          "quantity": 1
        },
        {
          "id": "obj-move-to-watson",
          "description": "Переместиться в Watson",
          "type": "location",
          "target": {
            "type": "location",
            "id": "loc-watson-001"
          },
          "quantity": 1
        },
        {
          "id": "obj-find-rita",
          "description": "Найти Риту Морено в Watson",
          "type": "npc",
          "target": {
            "type": "npc",
            "id": "npc-rita-moreno"
          },
          "quantity": 1
        },
        {
          "id": "obj-deliver-package",
          "description": "Передать посылку Рите Морено",
          "type": "delivery",
          "target": {
            "type": "npc",
            "id": "npc-rita-moreno"
          },
          "quantity": 1
        }
      ],
      "rewards": {
        "experience": 100,
        "money": 200,
        "items": [],
        "reputation": {
          "faction": "ncpd",
          "amount": 5
        }
      },
      "requirements": {
        "level": 1,
        "reputation": null,
        "completedQuests": []
      }
    },
    {
      "id": "quest-find-trader-001",
      "name": "Найти торговца",
      "description": "Фиксер Марко \"Фикс\" Санчес просит найти торговца Джейка Арчера в Downtown и поговорить с ним о поставке. Это простое задание, но нужно знать, где искать.",
      "type": "side",
      "giverNpcId": "npc-marco-fix",
      "level": 1,
      "objectives": [
        {
          "id": "obj-accept-quest",
          "description": "Принять квест от Марко \"Фикс\" Санчеса",
          "type": "npc",
          "target": {
            "type": "npc",
            "id": "npc-marco-fix"
          },
          "quantity": 1
        },
        {
          "id": "obj-move-to-downtown",
          "description": "Переместиться в Downtown",
          "type": "location",
          "target": {
            "type": "location",
            "id": "loc-downtown-001"
          },
          "quantity": 1
        },
        {
          "id": "obj-find-jake",
          "description": "Найти Джейка Арчера в Downtown",
          "type": "npc",
          "target": {
            "type": "npc",
            "id": "npc-jake-archer"
          },
          "quantity": 1
        },
        {
          "id": "obj-talk-about-supply",
          "description": "Поговорить с Джейком о поставке",
          "type": "npc",
          "target": {
            "type": "npc",
            "id": "npc-jake-archer"
          },
          "quantity": 1
        }
      ],
      "rewards": {
        "experience": 150,
        "money": 250,
        "items": [],
        "reputation": {
          "faction": "independent",
          "amount": 5
        }
      },
      "requirements": {
        "level": 1,
        "reputation": null,
        "completedQuests": []
      }
    },
    {
      "id": "quest-package-delivery-001",
      "name": "Доставка посылки",
      "description": "Рабочая Анна Петрова просит доставить посылку из Santo Domingo в Watson. Путь может быть опасным, но если быть осторожным, все будет хорошо.",
      "type": "side",
      "giverNpcId": "npc-anna-petrova",
      "level": 2,
      "objectives": [
        {
          "id": "obj-accept-quest",
          "description": "Принять квест от Анны Петровой",
          "type": "npc",
          "target": {
            "type": "npc",
            "id": "npc-anna-petrova"
          },
          "quantity": 1
        },
        {
          "id": "obj-get-package",
          "description": "Получить посылку",
          "type": "item",
          "target": {
            "type": "item",
            "id": "item-package-delivery"
          },
          "quantity": 1
        },
        {
          "id": "obj-move-to-watson",
          "description": "Переместиться в Watson",
          "type": "location",
          "target": {
            "type": "location",
            "id": "loc-watson-001"
          },
          "quantity": 1
        },
        {
          "id": "obj-deliver-package",
          "description": "Передать посылку получателю",
          "type": "delivery",
          "target": {
            "type": "npc",
            "id": "npc-marco-fix"
          },
          "quantity": 1
        }
      ],
      "rewards": {
        "experience": 200,
        "money": 300,
        "items": ["item-medkit-basic"],
        "reputation": null
      },
      "requirements": {
        "level": 2,
        "reputation": null,
        "completedQuests": []
      }
    },
    {
      "id": "quest-show-respect-001",
      "name": "Показать уважение",
      "description": "Лидер банды Valentinos Хосе \"Тигр\" Рамирес просит выполнить задание, чтобы показать уважение к банде. Это опасное задание для опытных игроков.",
      "type": "side",
      "giverNpcId": "npc-jose-tiger",
      "level": 5,
      "objectives": [
        {
          "id": "obj-get-access",
          "description": "Получить доступ к Хосе \"Тигр\" Рамиресу (требуется репутация или выполнение предварительных заданий)",
          "type": "npc",
          "target": {
            "type": "npc",
            "id": "npc-jose-tiger"
          },
          "quantity": 1
        },
        {
          "id": "obj-accept-quest",
          "description": "Принять квест",
          "type": "npc",
          "target": {
            "type": "npc",
            "id": "npc-jose-tiger"
          },
          "quantity": 1
        },
        {
          "id": "obj-complete-task",
          "description": "Выполнить задание (детали зависят от реализации)",
          "type": "kill",
          "target": {
            "type": "enemy",
            "id": "npc-gangster-generic"
          },
          "quantity": 3
        },
        {
          "id": "obj-return-to-jose",
          "description": "Вернуться к Хосе",
          "type": "npc",
          "target": {
            "type": "npc",
            "id": "npc-jose-tiger"
          },
          "quantity": 1
        }
      ],
      "rewards": {
        "experience": 500,
        "money": 500,
        "items": [],
        "reputation": {
          "faction": "valentinos",
          "amount": 10
        }
      },
      "requirements": {
        "level": 5,
        "reputation": {
          "faction": "valentinos",
          "minValue": 0
        },
        "completedQuests": []
      }
    },
    {
      "id": "quest-first-combat-001",
      "name": "Первый бой",
      "description": "Фиксер Марко просит разобраться с бандитами в Watson. Это первый бой для игрока. Нужно быть готовым к опасности.",
      "type": "side",
      "giverNpcId": "npc-marco-fix",
      "level": 3,
      "objectives": [
        {
          "id": "obj-accept-quest",
          "description": "Принять квест от Марко",
          "type": "npc",
          "target": {
            "type": "npc",
            "id": "npc-marco-fix"
          },
          "quantity": 1
        },
        {
          "id": "obj-find-gangsters",
          "description": "Найти бандитов в Watson",
          "type": "location",
          "target": {
            "type": "location",
            "id": "loc-watson-001"
          },
          "quantity": 1
        },
        {
          "id": "obj-defeat-gangsters",
          "description": "Победить бандитов в бою (если бой реализован в MVP)",
          "type": "kill",
          "target": {
            "type": "enemy",
            "id": "npc-gangster-generic"
          },
          "quantity": 2
        },
        {
          "id": "obj-return-to-marco",
          "description": "Вернуться к Марко",
          "type": "npc",
          "target": {
            "type": "npc",
            "id": "npc-marco-fix"
          },
          "quantity": 1
        }
      ],
      "rewards": {
        "experience": 300,
        "money": 400,
        "items": [],
        "reputation": null
      },
      "requirements": {
        "level": 3,
        "reputation": null,
        "completedQuests": []
      }
    }
    ,
    {
      "id": "quest-merchant-defense-002",
      "name": "Защита торговца",
      "description": "Рита Морено просит защитить ее от бандитов в Watson. Это первый боевой квест для новичка; можно попытаться решить конфликт переговором (COOL проверка) или вступить в бой.",
      "type": "side",
      "giverNpcId": "npc-rita-moreno",
      "level": 1,
      "objectives": [
        {
          "id": "obj-accept-quest",
          "description": "Принять квест у Риты Морено",
          "type": "npc",
          "target": { "type": "npc", "id": "npc-rita-moreno" },
          "quantity": 1
        },
        {
          "id": "obj-defeat-bandits",
          "description": "Победить бандитов (или убедить их уйти)",
          "type": "kill",
          "target": { "type": "enemy", "id": "npc-gangster-generic" },
          "quantity": 2
        },
        {
          "id": "obj-return-to-rita",
          "description": "Вернуться к Рите Морено",
          "type": "npc",
          "target": { "type": "npc", "id": "npc-rita-moreno" },
          "quantity": 1
        }
      ],
      "rewards": {
        "experience": 150,
        "money": 400,
        "items": ["item-medkit-basic", "item-components-basic"],
        "reputation": { "faction": "independent", "amount": 5 }
      },
      "requirements": {
        "level": 1,
        "reputation": null,
        "completedQuests": ["quest-delivery-001"]
      }
    }
    ,
    {
      "id": "quest-main-2020-echoes-of-war",
      "name": "Эхо войны (2020)",
      "description": "Фиксер Марко просит найти следы прокси-конфликтов начала 2010-х: собрать тех-свидетельства корпоративных диверсий в Downtown.",
      "type": "main",
      "giverNpcId": "npc-marco-fix",
      "level": 2,
      "objectives": [
        { "id": "obj-accept", "description": "Принять задание у Марко", "type": "npc", "target": { "type": "npc", "id": "npc-marco-fix" }, "quantity": 1 },
        { "id": "obj-move", "description": "Переместиться в Downtown", "type": "location", "target": { "type": "location", "id": "loc-downtown-001" }, "quantity": 1 },
        { "id": "obj-collect", "description": "Собрать тех-свидетельство (электроника)", "type": "item", "target": { "type": "item", "id": "item-electronics-standard" }, "quantity": 1 },
        { "id": "obj-return", "description": "Вернуться к Марко", "type": "npc", "target": { "type": "npc", "id": "npc-marco-fix" }, "quantity": 1 }
      ],
      "rewards": { "experience": 240, "money": 300, "items": [], "reputation": null },
      "requirements": { "level": 2, "reputation": null, "completedQuests": [] }
    }
    ,
    {
      "id": "quest-main-2023-shattered-city",
      "name": "Разбитый город (2023)",
      "description": "Анна просит помочь в восстановлении: зачистить опасный участок и добыть запчасти для энергосети в Watson.",
      "type": "main",
      "giverNpcId": "npc-anna-petrova",
      "level": 3,
      "objectives": [
        { "id": "obj-accept", "description": "Принять задание у Анны", "type": "npc", "target": { "type": "npc", "id": "npc-anna-petrova" }, "quantity": 1 },
        { "id": "obj-move", "description": "Переместиться в Watson", "type": "location", "target": { "type": "location", "id": "loc-watson-001" }, "quantity": 1 },
        { "id": "obj-clear", "description": "Нейтрализовать угрозы (2)", "type": "kill", "target": { "type": "enemy", "id": "npc-gangster-generic" }, "quantity": 2 },
        { "id": "obj-collect", "description": "Собрать электронику (2)", "type": "item", "target": { "type": "item", "id": "item-electronics-standard" }, "quantity": 2 },
        { "id": "obj-return", "description": "Вернуться к Анне", "type": "npc", "target": { "type": "npc", "id": "npc-anna-petrova" }, "quantity": 1 }
      ],
      "rewards": { "experience": 320, "money": 360, "items": ["item-components-basic"], "reputation": null },
      "requirements": { "level": 3, "reputation": null, "completedQuests": ["quest-main-2020-echoes-of-war"] }
    }
    ,
    {
      "id": "quest-main-2025-blackwall-line",
      "name": "Линия Blackwall (2025)",
      "description": "Марко получает заказ на сбор телеметрии для локальных протоколов безопасности Blackwall. Нужно аккуратно действовать в корпоративной зоне.",
      "type": "main",
      "giverNpcId": "npc-marco-fix",
      "level": 4,
      "objectives": [
        { "id": "obj-accept", "description": "Принять задание у Марко", "type": "npc", "target": { "type": "npc", "id": "npc-marco-fix" }, "quantity": 1 },
        { "id": "obj-move", "description": "Переместиться в Downtown", "type": "location", "target": { "type": "location", "id": "loc-downtown-001" }, "quantity": 1 },
        { "id": "obj-collect", "description": "Получить телеметрию (электроника)", "type": "item", "target": { "type": "item", "id": "item-electronics-standard" }, "quantity": 1 },
        { "id": "obj-return", "description": "Вернуться к Марко", "type": "npc", "target": { "type": "npc", "id": "npc-marco-fix" }, "quantity": 1 }
      ],
      "rewards": { "experience": 360, "money": 420, "items": [], "reputation": null },
      "requirements": { "level": 4, "reputation": null, "completedQuests": ["quest-main-2023-shattered-city"] }
    }
    ,
    {
      "id": "quest-main-2035-free-city-charter",
      "name": "Хартия Свободного города (2035)",
      "description": "Офицер Миллер просит содействия: обеспечить порядок при переговорах по городскому уставу в эпоху восстановления.",
      "type": "main",
      "giverNpcId": "npc-sarah-miller",
      "level": 5,
      "objectives": [
        { "id": "obj-accept", "description": "Принять задание у Сары Миллер", "type": "npc", "target": { "type": "npc", "id": "npc-sarah-miller" }, "quantity": 1 },
        { "id": "obj-move", "description": "Переместиться в Westbrook", "type": "location", "target": { "type": "location", "id": "loc-westbrook-001" }, "quantity": 1 },
        { "id": "obj-consult", "description": "Проконсультироваться с Элизабет Чен", "type": "npc", "target": { "type": "npc", "id": "npc-elizabeth-chen" }, "quantity": 1 },
        { "id": "obj-return", "description": "Вернуться к Саре Миллер", "type": "npc", "target": { "type": "npc", "id": "npc-sarah-miller" }, "quantity": 1 }
      ],
      "rewards": { "experience": 420, "money": 480, "items": [], "reputation": { "faction": "ncpd", "amount": 8 } },
      "requirements": { "level": 5, "reputation": null, "completedQuests": ["quest-main-2025-blackwall-line"] }
    }
    ,
    {
      "id": "quest-main-2069-border-of-power",
      "name": "Граница власти (2069)",
      "description": "Элизабет Чен вовлекает вас в корпоративный спор вокруг статуса Свободного города. Нужны доказательства и сила.",
      "type": "main",
      "giverNpcId": "npc-elizabeth-chen",
      "level": 7,
      "objectives": [
        { "id": "obj-accept", "description": "Принять задание у Элизабет Чен", "type": "npc", "target": { "type": "npc", "id": "npc-elizabeth-chen" }, "quantity": 1 },
        { "id": "obj-move", "description": "Переместиться в Westbrook", "type": "location", "target": { "type": "location", "id": "loc-westbrook-001" }, "quantity": 1 },
        { "id": "obj-clear", "description": "Зачистить враждебных агентов (3)", "type": "kill", "target": { "type": "enemy", "id": "npc-gangster-generic" }, "quantity": 3 },
        { "id": "obj-return", "description": "Вернуться к Элизабет Чен", "type": "npc", "target": { "type": "npc", "id": "npc-elizabeth-chen" }, "quantity": 1 }
      ],
      "rewards": { "experience": 560, "money": 700, "items": [], "reputation": null },
      "requirements": { "level": 7, "reputation": null, "completedQuests": ["quest-main-2035-free-city-charter"] }
    }
    ,
    {
      "id": "quest-main-2077-relics-shadow",
      "name": "Тень ‘Реликта’ (2077)",
      "description": "Виктор Вектор просит проверить слухи о всплывших прототипах интерфейсов, связанных с легендарным проектом.",
      "type": "main",
      "giverNpcId": "npc-victor-vector",
      "level": 8,
      "objectives": [
        { "id": "obj-accept", "description": "Принять просьбу Виктора", "type": "npc", "target": { "type": "npc", "id": "npc-victor-vector" }, "quantity": 1 },
        { "id": "obj-move", "description": "Переместиться в Downtown", "type": "location", "target": { "type": "location", "id": "loc-downtown-001" }, "quantity": 1 },
        { "id": "obj-collect", "description": "Получить тех-данные (электроника)", "type": "item", "target": { "type": "item", "id": "item-electronics-standard" }, "quantity": 1 },
        { "id": "obj-return", "description": "Вернуться к Виктору", "type": "npc", "target": { "type": "npc", "id": "npc-victor-vector" }, "quantity": 1 }
      ],
      "rewards": { "experience": 620, "money": 780, "items": [], "reputation": null },
      "requirements": { "level": 8, "reputation": null, "completedQuests": ["quest-main-2069-border-of-power"] }
    }
    ,
    {
      "id": "quest-main-2093-net-shift",
      "name": "Сдвиг Сети (2093)",
      "description": "Элизабет сообщает о 'серой стене' — новом феномене на границе Blackwall. Нужно исследовать и обеспечить безопасность.",
      "type": "main",
      "giverNpcId": "npc-elizabeth-chen",
      "level": 10,
      "objectives": [
        { "id": "obj-accept", "description": "Принять задание у Элизабет Чен", "type": "npc", "target": { "type": "npc", "id": "npc-elizabeth-chen" }, "quantity": 1 },
        { "id": "obj-move", "description": "Переместиться в Downtown", "type": "location", "target": { "type": "location", "id": "loc-downtown-001" }, "quantity": 1 },
        { "id": "obj-clear", "description": "Зачистить аномальные угрозы (3)", "type": "kill", "target": { "type": "enemy", "id": "npc-gangster-generic" }, "quantity": 3 },
        { "id": "obj-collect", "description": "Получить диагностические логи (электроника)", "type": "item", "target": { "type": "item", "id": "item-electronics-standard" }, "quantity": 1 },
        { "id": "obj-return", "description": "Вернуться к Элизабет Чен", "type": "npc", "target": { "type": "npc", "id": "npc-elizabeth-chen" }, "quantity": 1 }
      ],
      "rewards": { "experience": 900, "money": 1200, "items": [], "reputation": null },
      "requirements": { "level": 10, "reputation": null, "completedQuests": ["quest-main-2077-relics-shadow"] }
    }
    ,
    {
      "id": "quest-side-2030-supply-disruption",
      "name": "Нарушение поставок (2030)",
      "description": "Торговец Джейк Арчер просит разобраться с бандой, которая перехватывает его поставки между Downtown и Watson.",
      "type": "side",
      "giverNpcId": "npc-jake-archer",
      "level": 3,
      "objectives": [
        { "id": "obj-accept", "description": "Принять задание у Джейка", "type": "npc", "target": { "type": "npc", "id": "npc-jake-archer" }, "quantity": 1 },
        { "id": "obj-investigate", "description": "Исследовать место перехвата (Watson)", "type": "location", "target": { "type": "location", "id": "loc-watson-001" }, "quantity": 1 },
        { "id": "obj-clear-bandits", "description": "Нейтрализовать бандитов (3)", "type": "kill", "target": { "type": "enemy", "id": "npc-gangster-generic" }, "quantity": 3 },
        { "id": "obj-recover-goods", "description": "Вернуть украденный груз", "type": "item", "target": { "type": "item", "id": "item-electronics-standard" }, "quantity": 2 },
        { "id": "obj-return", "description": "Вернуться к Джейку", "type": "npc", "target": { "type": "npc", "id": "npc-jake-archer" }, "quantity": 1 }
      ],
      "rewards": { "experience": 280, "money": 380, "items": ["item-medkit-basic"], "reputation": { "faction": "independent", "amount": 5 } },
      "requirements": { "level": 3, "reputation": null, "completedQuests": [] },
      "metadata": {
        "skillChecks": [
          { "type": "perception", "dc": 12, "bonus": "reveal-ambush", "description": "Заметить засаду заранее" },
          { "type": "cool", "dc": 13, "bonus": "negotiate", "description": "Договориться с бандитами без боя" }
        ]
      }
    }
    ,
    {
      "id": "quest-main-2040-red-dawn",
      "name": "Красный рассвет (2040)",
      "description": "Марко просит помочь эвакуировать выживших из зоны поражения после взрыва 2023. Руины опасны, но люди нуждаются в помощи.",
      "type": "main",
      "giverNpcId": "npc-marco-fix",
      "level": 5,
      "objectives": [
        { "id": "obj-accept", "description": "Принять задание у Марко", "type": "npc", "target": { "type": "npc", "id": "npc-marco-fix" }, "quantity": 1 },
        { "id": "obj-move-ruins", "description": "Переместиться в руины Downtown", "type": "location", "target": { "type": "location", "id": "loc-downtown-001" }, "quantity": 1 },
        { "id": "obj-find-survivors", "description": "Найти выживших (3)", "type": "npc", "target": { "type": "npc", "id": "npc-anna-petrova" }, "quantity": 1 },
        { "id": "obj-clear-path", "description": "Зачистить путь от угроз (4)", "type": "kill", "target": { "type": "enemy", "id": "npc-gangster-generic" }, "quantity": 4 },
        { "id": "obj-escort", "description": "Сопроводить выживших в безопасное место", "type": "location", "target": { "type": "location", "id": "loc-watson-001" }, "quantity": 1 },
        { "id": "obj-return", "description": "Вернуться к Марко", "type": "npc", "target": { "type": "npc", "id": "npc-marco-fix" }, "quantity": 1 }
      ],
      "rewards": { "experience": 480, "money": 520, "items": ["item-components-basic"], "reputation": { "faction": "independent", "amount": 10 } },
      "requirements": { "level": 5, "reputation": null, "completedQuests": ["quest-main-2035-free-city-charter"] },
      "metadata": {
        "skillChecks": [
          { "type": "tech", "dc": 14, "bonus": "repair-shield", "description": "Починить защитные экраны для безопасного прохода" },
          { "type": "medical", "dc": 12, "bonus": "heal-survivors", "description": "Оказать первую помощь выжившим (+XP)" }
        ],
        "environment": "red-dust-zone",
        "hazards": ["radiation", "collapsed-buildings", "hostile-scavs"]
      }
    }
    ,
    {
      "id": "quest-side-2045-scav-problem",
      "name": "Проблема скавов (2045)",
      "description": "Рита Морено жалуется на скавов, охотящихся за имплантами в Watson. Нужно показать им, что этот район под защитой.",
      "type": "side",
      "giverNpcId": "npc-rita-moreno",
      "level": 4,
      "objectives": [
        { "id": "obj-accept", "description": "Принять задание у Риты", "type": "npc", "target": { "type": "npc", "id": "npc-rita-moreno" }, "quantity": 1 },
        { "id": "obj-track", "description": "Выследить логово скавов", "type": "location", "target": { "type": "location", "id": "loc-watson-001" }, "quantity": 1 },
        { "id": "obj-eliminate", "description": "Нейтрализовать скавов (5)", "type": "kill", "target": { "type": "enemy", "id": "npc-gangster-generic" }, "quantity": 5 },
        { "id": "obj-evidence", "description": "Собрать доказательства (украденные импланты)", "type": "item", "target": { "type": "item", "id": "item-electronics-standard" }, "quantity": 2 },
        { "id": "obj-return", "description": "Вернуться к Рите", "type": "npc", "target": { "type": "npc", "id": "npc-rita-moreno" }, "quantity": 1 }
      ],
      "rewards": { "experience": 340, "money": 420, "items": ["item-medkit-basic"], "reputation": { "faction": "independent", "amount": 8 } },
      "requirements": { "level": 4, "reputation": null, "completedQuests": [] },
      "metadata": {
        "skillChecks": [
          { "type": "tracking", "dc": 13, "bonus": "find-hideout-fast", "description": "Быстро найти убежище скавов" },
          { "type": "intimidation", "dc": 14, "bonus": "scare-off", "description": "Напугать скавов, чтобы они покинули район" }
        ]
      }
    }
    ,
    {
      "id": "quest-main-2050-network-recovery",
      "name": "Восстановление Сети (2050)",
      "description": "Элизабет Чен нанимает нетраннера для восстановления локальной сетевой инфраструктуры после DataKrash. Это опасно — старые ИИ могут быть все еще активны.",
      "type": "main",
      "giverNpcId": "npc-elizabeth-chen",
      "level": 6,
      "objectives": [
        { "id": "obj-accept", "description": "Принять задание у Элизабет", "type": "npc", "target": { "type": "npc", "id": "npc-elizabeth-chen" }, "quantity": 1 },
        { "id": "obj-access-node", "description": "Получить доступ к узлу (Downtown)", "type": "location", "target": { "type": "location", "id": "loc-downtown-001" }, "quantity": 1 },
        { "id": "obj-clear-corrupted", "description": "Очистить поврежденные данные (взлом)", "type": "item", "target": { "type": "item", "id": "item-electronics-standard" }, "quantity": 3 },
        { "id": "obj-combat", "description": "Противостоять враждебным программам (боевые прокси)", "type": "kill", "target": { "type": "enemy", "id": "npc-gangster-generic" }, "quantity": 3 },
        { "id": "obj-restore", "description": "Восстановить сетевой узел", "type": "location", "target": { "type": "location", "id": "loc-downtown-001" }, "quantity": 1 },
        { "id": "obj-return", "description": "Вернуться к Элизабет", "type": "npc", "target": { "type": "npc", "id": "npc-elizabeth-chen" }, "quantity": 1 }
      ],
      "rewards": { "experience": 520, "money": 640, "items": [], "reputation": { "faction": "independent", "amount": 12 } },
      "requirements": { "level": 6, "reputation": null, "completedQuests": ["quest-main-2040-red-dawn"] },
      "metadata": {
        "skillChecks": [
          { "type": "int", "dc": 15, "bonus": "bypass-firewall", "description": "Обойти старые файрволы" },
          { "type": "tech", "dc": 14, "bonus": "repair-node", "description": "Починить физические повреждения узла" }
        ],
        "netrunnerRequired": true
      }
    }
    ,
    {
      "id": "quest-faction-6th-street-2055",
      "name": "Патриотический долг (2055)",
      "description": "6th Street просит помощи в защите Santo Domingo от банд. Они позиционируют себя как защитники простых людей.",
      "type": "side",
      "giverNpcId": "npc-anna-petrova",
      "level": 5,
      "objectives": [
        { "id": "obj-accept", "description": "Принять задание у Анны", "type": "npc", "target": { "type": "npc", "id": "npc-anna-petrova" }, "quantity": 1 },
        { "id": "obj-patrol", "description": "Патрулировать Santo Domingo", "type": "location", "target": { "type": "location", "id": "loc-santo-domingo-001" }, "quantity": 1 },
        { "id": "obj-engage", "description": "Отразить нападение банды (4)", "type": "kill", "target": { "type": "enemy", "id": "npc-gangster-generic" }, "quantity": 4 },
        { "id": "obj-return", "description": "Отчитаться перед Анной", "type": "npc", "target": { "type": "npc", "id": "npc-anna-petrova" }, "quantity": 1 }
      ],
      "rewards": { "experience": 420, "money": 480, "items": [], "reputation": { "faction": "6th-street", "amount": 15 } },
      "requirements": { "level": 5, "reputation": null, "completedQuests": [] },
      "metadata": {
        "skillChecks": [
          { "type": "tactics", "dc": 14, "bonus": "ambush-setup", "description": "Организовать засаду для банды" }
        ]
      }
    }
    ,
    {
      "id": "quest-main-2060-corp-return",
      "name": "Возвращение корпораций (2060)",
      "description": "Сара Миллер сообщает о возвращении корпоративного присутствия в городе. NCPD нужна помощь в мониторинге ситуации.",
      "type": "main",
      "giverNpcId": "npc-sarah-miller",
      "level": 6,
      "objectives": [
        { "id": "obj-accept", "description": "Принять задание у Сары", "type": "npc", "target": { "type": "npc", "id": "npc-sarah-miller" }, "quantity": 1 },
        { "id": "obj-surveillance", "description": "Провести наблюдение в Westbrook", "type": "location", "target": { "type": "location", "id": "loc-westbrook-001" }, "quantity": 1 },
        { "id": "obj-gather-intel", "description": "Собрать корпоративные данные", "type": "item", "target": { "type": "item", "id": "item-electronics-standard" }, "quantity": 2 },
        { "id": "obj-confront", "description": "Противостоять корпоративным оперативникам (3)", "type": "kill", "target": { "type": "enemy", "id": "npc-gangster-generic" }, "quantity": 3 },
        { "id": "obj-return", "description": "Вернуться к Саре", "type": "npc", "target": { "type": "npc", "id": "npc-sarah-miller" }, "quantity": 1 }
      ],
      "rewards": { "experience": 540, "money": 660, "items": [], "reputation": { "faction": "ncpd", "amount": 10 } },
      "requirements": { "level": 6, "reputation": null, "completedQuests": ["quest-main-2050-network-recovery"] },
      "metadata": {
        "skillChecks": [
          { "type": "stealth", "dc": 15, "bonus": "undetected", "description": "Провести наблюдение незаметно" },
          { "type": "cool", "dc": 14, "bonus": "talk-down", "description": "Договориться с оперативниками" }
        ]
      }
    }
    ,
    {
      "id": "quest-side-2065-implant-rush",
      "name": "Имплант-лихорадка (2065)",
      "description": "Виктор Вектор обеспокоен ростом случаев киберпсихоза из-за новых военных имплантов. Нужно найти источник и остановить нелегальную торговлю.",
      "type": "side",
      "giverNpcId": "npc-victor-vector",
      "level": 7,
      "objectives": [
        { "id": "obj-accept", "description": "Принять задание у Виктора", "type": "npc", "target": { "type": "npc", "id": "npc-victor-vector" }, "quantity": 1 },
        { "id": "obj-investigate", "description": "Расследовать случаи в Watson", "type": "location", "target": { "type": "location", "id": "loc-watson-001" }, "quantity": 1 },
        { "id": "obj-find-dealer", "description": "Найти торговца нелегальными имплантами", "type": "npc", "target": { "type": "npc", "id": "npc-gangster-generic" }, "quantity": 1 },
        { "id": "obj-confront-supplier", "description": "Противостоять поставщикам (4)", "type": "kill", "target": { "type": "enemy", "id": "npc-gangster-generic" }, "quantity": 4 },
        { "id": "obj-confiscate", "description": "Конфисковать опасные импланты", "type": "item", "target": { "type": "item", "id": "item-electronics-standard" }, "quantity": 3 },
        { "id": "obj-return", "description": "Вернуться к Виктору", "type": "npc", "target": { "type": "npc", "id": "npc-victor-vector" }, "quantity": 1 }
      ],
      "rewards": { "experience": 580, "money": 720, "items": ["item-components-basic"], "reputation": { "faction": "independent", "amount": 15 } },
      "requirements": { "level": 7, "reputation": null, "completedQuests": [] },
      "metadata": {
        "skillChecks": [
          { "type": "medical", "dc": 15, "bonus": "identify-implant", "description": "Определить происхождение имплантов" },
          { "type": "intimidation", "dc": 14, "bonus": "scare-dealer", "description": "Напугать торговца для получения информации" }
        ]
      }
    }
    ,
    {
      "id": "quest-main-2070-nusa-tensions",
      "name": "Напряжение с NUSA (2070)",
      "description": "Элизабет Чен предупреждает о растущих противоречиях между Найт-Сити и NUSA. Нужно собрать разведданные о возможной интервенции.",
      "type": "main",
      "giverNpcId": "npc-elizabeth-chen",
      "level": 7,
      "objectives": [
        { "id": "obj-accept", "description": "Принять задание у Элизабет", "type": "npc", "target": { "type": "npc", "id": "npc-elizabeth-chen" }, "quantity": 1 },
        { "id": "obj-meet-informant", "description": "Встретиться с информатором (Downtown)", "type": "location", "target": { "type": "location", "id": "loc-downtown-001" }, "quantity": 1 },
        { "id": "obj-infiltrate", "description": "Проникнуть в NUSA представительство", "type": "location", "target": { "type": "location", "id": "loc-westbrook-001" }, "quantity": 1 },
        { "id": "obj-steal-data", "description": "Украсть разведданные", "type": "item", "target": { "type": "item", "id": "item-electronics-standard" }, "quantity": 2 },
        { "id": "obj-escape", "description": "Избежать преследования (4 агента)", "type": "kill", "target": { "type": "enemy", "id": "npc-gangster-generic" }, "quantity": 4 },
        { "id": "obj-return", "description": "Вернуться к Элизабет", "type": "npc", "target": { "type": "npc", "id": "npc-elizabeth-chen" }, "quantity": 1 }
      ],
      "rewards": { "experience": 640, "money": 800, "items": [], "reputation": { "faction": "independent", "amount": 20 } },
      "requirements": { "level": 7, "reputation": null, "completedQuests": ["quest-main-2060-corp-return"] },
      "metadata": {
        "skillChecks": [
          { "type": "stealth", "dc": 16, "bonus": "silent-infiltration", "description": "Проникнуть незаметно" },
          { "type": "int", "dc": 15, "bonus": "hack-terminal", "description": "Взломать защищенный терминал" },
          { "type": "cool", "dc": 16, "bonus": "bluff-guards", "description": "Обмануть охрану" }
        ],
        "highRisk": true
      }
    }
    ,
    {
      "id": "quest-side-2075-street-war",
      "name": "Уличная война (2075)",
      "description": "Марко просит вмешаться в конфликт между Valentinos и Maelstrom, который угрожает перерасти в полномасштабную войну.",
      "type": "side",
      "giverNpcId": "npc-marco-fix",
      "level": 8,
      "objectives": [
        { "id": "obj-accept", "description": "Принять задание у Марко", "type": "npc", "target": { "type": "npc", "id": "npc-marco-fix" }, "quantity": 1 },
        { "id": "obj-investigate", "description": "Расследовать причины конфликта", "type": "location", "target": { "type": "location", "id": "loc-watson-001" }, "quantity": 1 },
        { "id": "obj-meet-valentinos", "description": "Встретиться с представителем Valentinos", "type": "npc", "target": { "type": "npc", "id": "npc-jose-tiger" }, "quantity": 1 },
        { "id": "obj-choice", "description": "Сделать выбор: помочь одной стороне или остановить конфликт", "type": "choice", "target": null, "quantity": 1 },
        { "id": "obj-combat", "description": "Участвовать в схватке (5 врагов)", "type": "kill", "target": { "type": "enemy", "id": "npc-gangster-generic" }, "quantity": 5 },
        { "id": "obj-return", "description": "Вернуться к Марко", "type": "npc", "target": { "type": "npc", "id": "npc-marco-fix" }, "quantity": 1 }
      ],
      "rewards": { "experience": 680, "money": 860, "items": [], "reputation": { "faction": "valentinos", "amount": 15 } },
      "requirements": { "level": 8, "reputation": null, "completedQuests": [] },
      "metadata": {
        "skillChecks": [
          { "type": "cool", "dc": 17, "bonus": "mediate", "description": "Выступить посредником и остановить войну" },
          { "type": "intimidation", "dc": 16, "bonus": "threat", "description": "Угрозой заставить обе стороны отступить" }
        ],
        "choice": {
          "optionA": { "side": "valentinos", "reputation": { "valentinos": 20, "maelstrom": -20 } },
          "optionB": { "side": "maelstrom", "reputation": { "maelstrom": 20, "valentinos": -20 } },
          "optionC": { "side": "neutral", "reputation": { "independent": 15 } }
        }
      }
    }
    ,
    {
      "id": "quest-main-2080-corporate-shadow",
      "name": "Корпоративная тень (2080)",
      "description": "Сара Миллер расследует серию убийств, связанных с корпоративными экспериментами. NCPD нужна помощь того, кто не боится копать глубоко.",
      "type": "main",
      "giverNpcId": "npc-sarah-miller",
      "level": 9,
      "objectives": [
        { "id": "obj-accept", "description": "Принять задание у Сары", "type": "npc", "target": { "type": "npc", "id": "npc-sarah-miller" }, "quantity": 1 },
        { "id": "obj-crime-scene", "description": "Осмотреть место преступления (Downtown)", "type": "location", "target": { "type": "location", "id": "loc-downtown-001" }, "quantity": 1 },
        { "id": "obj-gather-clues", "description": "Собрать улики", "type": "item", "target": { "type": "item", "id": "item-electronics-standard" }, "quantity": 3 },
        { "id": "obj-trace", "description": "Выследить корпоративную лабораторию (Westbrook)", "type": "location", "target": { "type": "location", "id": "loc-westbrook-001" }, "quantity": 1 },
        { "id": "obj-infiltrate-lab", "description": "Проникнуть в лабораторию", "type": "location", "target": { "type": "location", "id": "loc-westbrook-001" }, "quantity": 1 },
        { "id": "obj-combat-guards", "description": "Противостоять охране (5)", "type": "kill", "target": { "type": "enemy", "id": "npc-gangster-generic" }, "quantity": 5 },
        { "id": "obj-destroy-evidence", "description": "Уничтожить незаконные эксперименты", "type": "item", "target": { "type": "item", "id": "item-electronics-standard" }, "quantity": 1 },
        { "id": "obj-return", "description": "Вернуться к Саре", "type": "npc", "target": { "type": "npc", "id": "npc-sarah-miller" }, "quantity": 1 }
      ],
      "rewards": { "experience": 760, "money": 980, "items": ["item-components-basic"], "reputation": { "faction": "ncpd", "amount": 20 } },
      "requirements": { "level": 9, "reputation": null, "completedQuests": ["quest-main-2070-nusa-tensions"] },
      "metadata": {
        "skillChecks": [
          { "type": "perception", "dc": 16, "bonus": "find-hidden-clues", "description": "Найти скрытые улики" },
          { "type": "tech", "dc": 17, "bonus": "hack-security", "description": "Взломать систему безопасности" },
          { "type": "medical", "dc": 15, "bonus": "analyze-experiments", "description": "Проанализировать эксперименты" }
        ],
        "morality": "grey-area"
      }
    }
    ,
    {
      "id": "quest-side-2085-nomad-passage",
      "name": "Проход номадов (2085)",
      "description": "Анна Петрова просит помочь номадам, которые хотят пройти через Найт-Сити. Некоторые банды против этого.",
      "type": "side",
      "giverNpcId": "npc-anna-petrova",
      "level": 8,
      "objectives": [
        { "id": "obj-accept", "description": "Принять задание у Анны", "type": "npc", "target": { "type": "npc", "id": "npc-anna-petrova" }, "quantity": 1 },
        { "id": "obj-meet-nomads", "description": "Встретиться с номадами на окраине", "type": "location", "target": { "type": "location", "id": "loc-watson-001" }, "quantity": 1 },
        { "id": "obj-negotiate", "description": "Договориться с бандами о безопасном проходе", "type": "npc", "target": { "type": "npc", "id": "npc-jose-tiger" }, "quantity": 1 },
        { "id": "obj-escort", "description": "Сопроводить конвой через город", "type": "location", "target": { "type": "location", "id": "loc-downtown-001" }, "quantity": 1 },
        { "id": "obj-defend", "description": "Защитить номадов от нападения (4)", "type": "kill", "target": { "type": "enemy", "id": "npc-gangster-generic" }, "quantity": 4 },
        { "id": "obj-return", "description": "Вернуться к Анне", "type": "npc", "target": { "type": "npc", "id": "npc-anna-petrova" }, "quantity": 1 }
      ],
      "rewards": { "experience": 620, "money": 760, "items": [], "reputation": { "faction": "nomads", "amount": 20 } },
      "requirements": { "level": 8, "reputation": null, "completedQuests": [] },
      "metadata": {
        "skillChecks": [
          { "type": "cool", "dc": 16, "bonus": "peaceful-passage", "description": "Договориться о безопасном проходе" },
          { "type": "driving", "dc": 15, "bonus": "fast-escort", "description": "Быстро провести конвой" }
        ]
      }
    }
    ,
    {
      "id": "quest-main-2090-simulation-whispers",
      "name": "Шепот симуляции (2090)",
      "description": "Виктор Вектор получил странные данные от пациента: упоминания о 'границах мира' и 'симуляции'. Нужно разобраться, что это значит.",
      "type": "main",
      "giverNpcId": "npc-victor-vector",
      "level": 10,
      "objectives": [
        { "id": "obj-accept", "description": "Принять задание у Виктора", "type": "npc", "target": { "type": "npc", "id": "npc-victor-vector" }, "quantity": 1 },
        { "id": "obj-find-patient", "description": "Найти пациента (Watson)", "type": "location", "target": { "type": "location", "id": "loc-watson-001" }, "quantity": 1 },
        { "id": "obj-interview", "description": "Допросить пациента", "type": "npc", "target": { "type": "npc", "id": "npc-gangster-generic" }, "quantity": 1 },
        { "id": "obj-access-net", "description": "Получить доступ к глубоким слоям Сети", "type": "location", "target": { "type": "location", "id": "loc-downtown-001" }, "quantity": 1 },
        { "id": "obj-uncover", "description": "Раскрыть аномалии в данных", "type": "item", "target": { "type": "item", "id": "item-electronics-standard" }, "quantity": 3 },
        { "id": "obj-face-truth", "description": "Противостоять защитникам симуляции (5)", "type": "kill", "target": { "type": "enemy", "id": "npc-gangster-generic" }, "quantity": 5 },
        { "id": "obj-return", "description": "Вернуться к Виктору", "type": "npc", "target": { "type": "npc", "id": "npc-victor-vector" }, "quantity": 1 }
      ],
      "rewards": { "experience": 940, "money": 1300, "items": [], "reputation": null },
      "requirements": { "level": 10, "reputation": null, "completedQuests": ["quest-main-2080-corporate-shadow"] },
      "metadata": {
        "skillChecks": [
          { "type": "int", "dc": 18, "bonus": "understand-simulation", "description": "Понять природу симуляции" },
          { "type": "cool", "dc": 17, "bonus": "resist-madness", "description": "Сопротивляться безумию от истины" }
        ],
        "storyImpact": "high",
        "philosophy": "simulation-theory"
      }
    }
    ,
    {
      "id": "quest-side-2092-final-stand",
      "name": "Последний рубеж (2092)",
      "description": "Марко просит помощи в защите Watson от окончательного захвата корпорациями. Это может быть последний шанс сохранить независимость района.",
      "type": "side",
      "giverNpcId": "npc-marco-fix",
      "level": 11,
      "objectives": [
        { "id": "obj-accept", "description": "Принять задание у Марко", "type": "npc", "target": { "type": "npc", "id": "npc-marco-fix" }, "quantity": 1 },
        { "id": "obj-rally", "description": "Собрать ополчение из местных", "type": "location", "target": { "type": "location", "id": "loc-watson-001" }, "quantity": 1 },
        { "id": "obj-fortify", "description": "Укрепить оборону района", "type": "item", "target": { "type": "item", "id": "item-components-basic" }, "quantity": 5 },
        { "id": "obj-first-wave", "description": "Отразить первую волну (6)", "type": "kill", "target": { "type": "enemy", "id": "npc-gangster-generic" }, "quantity": 6 },
        { "id": "obj-second-wave", "description": "Отразить вторую волну (8)", "type": "kill", "target": { "type": "enemy", "id": "npc-gangster-generic" }, "quantity": 8 },
        { "id": "obj-boss-fight", "description": "Победить корпоративного лидера", "type": "kill", "target": { "type": "enemy", "id": "npc-gangster-generic" }, "quantity": 1 },
        { "id": "obj-return", "description": "Вернуться к Марко", "type": "npc", "target": { "type": "npc", "id": "npc-marco-fix" }, "quantity": 1 }
      ],
      "rewards": { "experience": 1100, "money": 1500, "items": ["item-components-basic"], "reputation": { "faction": "independent", "amount": 30 } },
      "requirements": { "level": 11, "reputation": null, "completedQuests": [] },
      "metadata": {
        "skillChecks": [
          { "type": "leadership", "dc": 18, "bonus": "inspire-militia", "description": "Вдохновить ополчение на бой" },
          { "type": "tactics", "dc": 17, "bonus": "defense-strategy", "description": "Разработать эффективную стратегию обороны" }
        ],
        "epicBattle": true,
        "multipleWaves": true
      }
    }
    ,
    {
      "id": "quest-class-solo-2010-shadow-contract",
      "name": "Теневой контракт",
      "description": "Фиксер Марко предлагает соло скрытно ликвидировать угрозу, связанную с корпоративными прокси-конфликтами эпохи 2008–2010. Минимум шума, максимум эффекта.",
      "type": "side",
      "giverNpcId": "npc-marco-fix",
      "level": 2,
      "objectives": [
        { "id": "obj-accept-quest", "description": "Принять контракт у Марко", "type": "npc", "target": { "type": "npc", "id": "npc-marco-fix" }, "quantity": 1 },
        { "id": "obj-move-to-downtown", "description": "Переместиться в Downtown (корпоративная зона)", "type": "location", "target": { "type": "location", "id": "loc-downtown-001" }, "quantity": 1 },
        { "id": "obj-neutralize-targets", "description": "Нейтрализовать 2 цели прокси-банды", "type": "kill", "target": { "type": "enemy", "id": "npc-gangster-generic" }, "quantity": 2 },
        { "id": "obj-return-to-fix", "description": "Вернуться к Марко", "type": "npc", "target": { "type": "npc", "id": "npc-marco-fix" }, "quantity": 1 }
      ],
      "rewards": { "experience": 220, "money": 350, "items": [], "reputation": null },
      "requirements": { "level": 2, "reputation": null, "completedQuests": [] }
    }
    ,
    {
      "id": "quest-class-netrunner-2011-netwatch-signal",
      "name": "Сигнал NetWatch",
      "description": "Во время сетевых войн 2010–2011 всплыли уязвимости старой инфраструктуры. Фиксер просит извлечь данные о сигнатурах NetWatch с корпоративного узла.",
      "type": "side",
      "giverNpcId": "npc-marco-fix",
      "level": 2,
      "objectives": [
        { "id": "obj-accept-quest", "description": "Принять задание у Марко", "type": "npc", "target": { "type": "npc", "id": "npc-marco-fix" }, "quantity": 1 },
        { "id": "obj-reach-node", "description": "Добраться до корпоративного узла в Downtown", "type": "location", "target": { "type": "location", "id": "loc-downtown-001" }, "quantity": 1 },
        { "id": "obj-obtain-datashard", "description": "Получить даташард с сигнатурами (импровизация)", "type": "item", "target": { "type": "item", "id": "item-electronics-standard" }, "quantity": 1 },
        { "id": "obj-return", "description": "Вернуться к Марко с данными", "type": "npc", "target": { "type": "npc", "id": "npc-marco-fix" }, "quantity": 1 }
      ],
      "rewards": { "experience": 230, "money": 320, "items": [], "reputation": null },
      "requirements": { "level": 2, "reputation": null, "completedQuests": [] }
    }
    ,
    {
      "id": "quest-class-techie-2025-repair-grid",
      "name": "Сетевой ремонт",
      "description": "После разрушений 2023 начался ремонт городской инфраструктуры. Анна из Santo Domingo просит помочь восстановить узел энергосети.",
      "type": "side",
      "giverNpcId": "npc-anna-petrova",
      "level": 2,
      "objectives": [
        { "id": "obj-accept-quest", "description": "Принять задание у Анны", "type": "npc", "target": { "type": "npc", "id": "npc-anna-petrova" }, "quantity": 1 },
        { "id": "obj-move-to-sd", "description": "Переместиться в Santo Domingo", "type": "location", "target": { "type": "location", "id": "loc-santo-domingo-001" }, "quantity": 1 },
        { "id": "obj-collect-parts", "description": "Собрать электронику (2 шт.)", "type": "item", "target": { "type": "item", "id": "item-electronics-standard" }, "quantity": 2 },
        { "id": "obj-return-anna", "description": "Вернуться к Анне", "type": "npc", "target": { "type": "npc", "id": "npc-anna-petrova" }, "quantity": 1 }
      ],
      "rewards": { "experience": 220, "money": 280, "items": ["item-components-basic"], "reputation": null },
      "requirements": { "level": 2, "reputation": null, "completedQuests": [] }
    }
    ,
    {
      "id": "quest-faction-arasaka-legacy-2070",
      "name": "Наследие Реликта",
      "description": "Через корпоративного посредника вы получаете заказ на поиск следов технологического наследия проектов Arasaka времён 2070-х.",
      "type": "side",
      "giverNpcId": "npc-elizabeth-chen",
      "level": 4,
      "objectives": [
        { "id": "obj-accept", "description": "Принять задание у Элизабет Чен", "type": "npc", "target": { "type": "npc", "id": "npc-elizabeth-chen" }, "quantity": 1 },
        { "id": "obj-scout-corporate", "description": "Осмотреть корпоративные башни Westbrook", "type": "location", "target": { "type": "location", "id": "loc-westbrook-001" }, "quantity": 1 },
        { "id": "obj-recover-tech", "description": "Получить технологические данные (электроника)", "type": "item", "target": { "type": "item", "id": "item-electronics-standard" }, "quantity": 1 },
        { "id": "obj-return-chen", "description": "Вернуться к Элизабет Чен", "type": "npc", "target": { "type": "npc", "id": "npc-elizabeth-chen" }, "quantity": 1 }
      ],
      "rewards": { "experience": 380, "money": 600, "items": [], "reputation": { "faction": "independent", "amount": 5 } },
      "requirements": { "level": 4, "reputation": null, "completedQuests": [] }
    }
    ,
    {
      "id": "quest-faction-militech-contract-2065",
      "name": "Контракт Militech",
      "description": "Через корп-канал приходит запрос: проверить склад с вооружением, связанный с проектами Militech 2060-х.",
      "type": "side",
      "giverNpcId": "npc-elizabeth-chen",
      "level": 4,
      "objectives": [
        { "id": "obj-accept", "description": "Принять контракт у Элизабет Чен", "type": "npc", "target": { "type": "npc", "id": "npc-elizabeth-chen" }, "quantity": 1 },
        { "id": "obj-move-watson", "description": "Переместиться в Watson (склад)", "type": "location", "target": { "type": "location", "id": "loc-watson-001" }, "quantity": 1 },
        { "id": "obj-clear-hostiles", "description": "Зачистить враждебных (3)", "type": "kill", "target": { "type": "enemy", "id": "npc-gangster-generic" }, "quantity": 3 },
        { "id": "obj-return", "description": "Вернуться к Элизабет Чен", "type": "npc", "target": { "type": "npc", "id": "npc-elizabeth-chen" }, "quantity": 1 }
      ],
      "rewards": { "experience": 420, "money": 700, "items": [], "reputation": null },
      "requirements": { "level": 4, "reputation": null, "completedQuests": [] }
    }
    ,
    {
      "id": "quest-faction-valentinos-honor-2000s",
      "name": "Честь улиц",
      "description": "Хосе ‘Тигр’ поручает задание, отражающее кодекс Valentinos: защитить семью в конфликте с конкурентами.",
      "type": "side",
      "giverNpcId": "npc-jose-tiger",
      "level": 2,
      "objectives": [
        { "id": "obj-accept", "description": "Представиться Хосе и принять задание", "type": "npc", "target": { "type": "npc", "id": "npc-jose-tiger" }, "quantity": 1 },
        { "id": "obj-move-heywood", "description": "Переместиться в Heywood", "type": "location", "target": { "type": "location", "id": "loc-heywood-001" }, "quantity": 1 },
        { "id": "obj-protect", "description": "Отразить нападение (2 противника)", "type": "kill", "target": { "type": "enemy", "id": "npc-gangster-generic" }, "quantity": 2 },
        { "id": "obj-return-jose", "description": "Вернуться к Хосе", "type": "npc", "target": { "type": "npc", "id": "npc-jose-tiger" }, "quantity": 1 }
      ],
      "rewards": { "experience": 260, "money": 320, "items": [], "reputation": { "faction": "valentinos", "amount": 8 } },
      "requirements": { "level": 2, "reputation": null, "completedQuests": [] }
    }
    ,
    {
      "id": "quest-faction-maelstrom-salvage-2045",
      "name": "Железный трофей",
      "description": "После ‘Времени Красного’ в руинах полно хабара. Фиксер просит добыть тех-лом, который интересует Maelstrom.",
      "type": "side",
      "giverNpcId": "npc-marco-fix",
      "level": 3,
      "objectives": [
        { "id": "obj-accept", "description": "Принять задание у Марко", "type": "npc", "target": { "type": "npc", "id": "npc-marco-fix" }, "quantity": 1 },
        { "id": "obj-scavenge-watson", "description": "Собрать компоненты в Watson", "type": "item", "target": { "type": "item", "id": "item-components-basic" }, "quantity": 3 },
        { "id": "obj-clear-ambush", "description": "Отразить засаду мародёров", "type": "kill", "target": { "type": "enemy", "id": "npc-gangster-generic" }, "quantity": 2 },
        { "id": "obj-return-fix", "description": "Вернуться к Марко", "type": "npc", "target": { "type": "npc", "id": "npc-marco-fix" }, "quantity": 1 }
      ],
      "rewards": { "experience": 330, "money": 450, "items": [], "reputation": null },
      "requirements": { "level": 3, "reputation": null, "completedQuests": [] }
    }
    ,
    {
      "id": "quest-main-2020-proxy-wars-legacy",
      "name": "Наследие прокси-войн (2020)",
      "description": "Марко просит найти следы корпоративных прокси-конфликтов начала 2010-х. В Downtown есть заброшенная лаборатория, где проводились эксперименты. Нужно собрать доказательства.",
      "type": "main",
      "giverNpcId": "npc-marco-fix",
      "level": 2,
      "objectives": [
        { "id": "obj-accept", "description": "Принять задание у Марко", "type": "npc", "target": { "type": "npc", "id": "npc-marco-fix" }, "quantity": 1 },
        { "id": "obj-investigate", "description": "Исследовать заброшенную лабораторию (Downtown)", "type": "location", "target": { "type": "location", "id": "loc-downtown-001" }, "quantity": 1 },
        { "id": "obj-collect-evidence", "description": "Собрать доказательства (электроника)", "type": "item", "target": { "type": "item", "id": "item-electronics-standard" }, "quantity": 3 },
        { "id": "obj-clear-security", "description": "Обезвредить системы безопасности (2)", "type": "kill", "target": { "type": "enemy", "id": "npc-gangster-generic" }, "quantity": 2 },
        { "id": "obj-return", "description": "Вернуться к Марко", "type": "npc", "target": { "type": "npc", "id": "npc-marco-fix" }, "quantity": 1 }
      ],
      "rewards": { "experience": 240, "money": 300, "items": [], "reputation": { "faction": "independent", "amount": 5 } },
      "requirements": { "level": 2, "reputation": null, "completedQuests": [] },
      "metadata": {
        "skillChecks": [
          { "type": "perception", "dc": 12, "bonus": "find-hidden-evidence", "description": "Найти скрытые доказательства", "successEffects": { "item": "item-corporate-data", "xpBonus": 20 } },
          { "type": "tech", "dc": 13, "bonus": "disable-security", "description": "Отключить системы безопасности без боя", "successEffects": { "reduceEnemies": 2, "xpBonus": 30 } },
          { "type": "int", "dc": 12, "bonus": "understand-data", "description": "Понять ценность данных", "successEffects": { "moneyBonus": 50, "reputation": { "faction": "independent", "amount": 3 } } }
        ],
        "epoch": "2020-2030",
        "theme": "corporate-proxy-wars"
      }
    }
    ,
    {
      "id": "quest-side-2025-bartender-mystery",
      "name": "Тайна бармена (2025)",
      "description": "Бармен в Heywood просит помочь найти пропавшего друга. Последний раз его видели в Downtown. Нужно расследовать исчезновение.",
      "type": "side",
      "giverNpcId": "npc-jake-archer",
      "level": 3,
      "objectives": [
        { "id": "obj-accept", "description": "Принять задание", "type": "npc", "target": { "type": "npc", "id": "npc-jake-archer" }, "quantity": 1 },
        { "id": "obj-investigate", "description": "Расследовать исчезновение (Downtown)", "type": "location", "target": { "type": "location", "id": "loc-downtown-001" }, "quantity": 1 },
        { "id": "obj-find-clues", "description": "Найти улики (2)", "type": "item", "target": { "type": "item", "id": "item-electronics-standard" }, "quantity": 2 },
        { "id": "obj-rescue", "description": "Спасти друга (или найти тело)", "type": "npc", "target": { "type": "npc", "id": "npc-gangster-generic" }, "quantity": 1 },
        { "id": "obj-combat", "description": "Противостоять похитителям (3)", "type": "kill", "target": { "type": "enemy", "id": "npc-gangster-generic" }, "quantity": 3 },
        { "id": "obj-return", "description": "Вернуться к бармену", "type": "npc", "target": { "type": "npc", "id": "npc-jake-archer" }, "quantity": 1 }
      ],
      "rewards": { "experience": 300, "money": 400, "items": ["item-medkit-basic"], "reputation": { "faction": "independent", "amount": 8 } },
      "requirements": { "level": 3, "reputation": null, "completedQuests": [] },
      "metadata": {
        "skillChecks": [
          { "type": "investigation", "dc": 13, "bonus": "find-clues-fast", "description": "Быстро найти улики", "successEffects": { "timeReduction": 10, "xpBonus": 20 } },
          { "type": "cool", "dc": 14, "bonus": "negotiate-release", "description": "Договориться об освобождении без боя", "successEffects": { "reduceEnemies": 3, "reputation": { "faction": "independent", "amount": 5 } } },
          { "type": "medical", "dc": 12, "bonus": "save-friend", "description": "Спасти друга от смерти", "successEffects": { "xpBonus": 50, "reputation": { "faction": "independent", "amount": 10 } } }
        ],
        "branching": {
          "rescue": { "reputation": { "faction": "independent", "amount": 10 }, "xpBonus": 50 },
          "body": { "reputation": { "faction": "independent", "amount": 5 }, "xpBonus": 25 }
        }
      }
    }
    ,
    {
      "id": "quest-class-techie-2035-grid-stabilization",
      "name": "Стабилизация сетки (2035)",
      "description": "Энергосеть в Watson нестабильна. Техник-инженер просит помочь стабилизировать узлы. Нужно починить 3 узла и восстановить питание района.",
      "type": "side",
      "giverNpcId": "npc-anna-petrova",
      "level": 4,
      "objectives": [
        { "id": "obj-accept", "description": "Принять задание", "type": "npc", "target": { "type": "npc", "id": "npc-anna-petrova" }, "quantity": 1 },
        { "id": "obj-repair-node-1", "description": "Починить первый узел", "type": "location", "target": { "type": "location", "id": "loc-watson-001" }, "quantity": 1 },
        { "id": "obj-repair-node-2", "description": "Починить второй узел", "type": "location", "target": { "type": "location", "id": "loc-watson-001" }, "quantity": 1 },
        { "id": "obj-repair-node-3", "description": "Починить третий узел", "type": "location", "target": { "type": "location", "id": "loc-watson-001" }, "quantity": 1 },
        { "id": "obj-return", "description": "Вернуться к технику", "type": "npc", "target": { "type": "npc", "id": "npc-anna-petrova" }, "quantity": 1 }
      ],
      "rewards": { "experience": 360, "money": 450, "items": ["item-components-basic"], "reputation": { "faction": "independent", "amount": 12 } },
      "requirements": { "level": 4, "reputation": null, "completedQuests": [] },
      "metadata": {
        "skillChecks": [
          { "type": "tech", "dc": 14, "bonus": "repair-efficiently", "description": "Эффективно починить узел", "successEffects": { "timeReduction": 5, "xpBonus": 15 } },
          { "type": "int", "dc": 13, "bonus": "optimize-grid", "description": "Оптимизировать сеть", "successEffects": { "moneyBonus": 50, "reputation": { "faction": "independent", "amount": 3 } } }
        ],
        "classRequired": "techie",
        "classBonus": { "xpMultiplier": 1.2, "reputationBonus": 1.5 }
      }
    }
    ,
    {
      "id": "quest-faction-valentinos-2038-family-honor",
      "name": "Честь семьи (2038)",
      "description": "Хосе 'Тигр' Рамирес просит помочь в конфликте с другой бандой, которая оскорбила честь Valentinos. Нужно показать силу и уважение.",
      "type": "side",
      "giverNpcId": "npc-jose-tiger",
      "level": 4,
      "objectives": [
        { "id": "obj-accept", "description": "Принять задание у Хосе", "type": "npc", "target": { "type": "npc", "id": "npc-jose-tiger" }, "quantity": 1 },
        { "id": "obj-confront", "description": "Противостоять оскорбившей банде (Heywood)", "type": "location", "target": { "type": "location", "id": "loc-heywood-001" }, "quantity": 1 },
        { "id": "obj-combat", "description": "Победить лидеров банды (3)", "type": "kill", "target": { "type": "enemy", "id": "npc-gangster-generic" }, "quantity": 3 },
        { "id": "obj-return", "description": "Вернуться к Хосе", "type": "npc", "target": { "type": "npc", "id": "npc-jose-tiger" }, "quantity": 1 }
      ],
      "rewards": { "experience": 340, "money": 420, "items": [], "reputation": { "faction": "valentinos", "amount": 20 } },
      "requirements": { "level": 4, "reputation": { "faction": "valentinos", "min": 10 }, "completedQuests": [] },
      "metadata": {
        "skillChecks": [
          { "type": "cool", "dc": 15, "bonus": "intimidate-leaders", "description": "Устрашить лидеров без боя", "successEffects": { "reduceEnemies": 2, "reputation": { "faction": "valentinos", "amount": 5 } } },
          { "type": "intimidation", "dc": 14, "bonus": "show-strength", "description": "Показать силу и уважение", "successEffects": { "reputation": { "faction": "valentinos", "amount": 10 } } }
        ],
        "factionRequired": "valentinos",
        "factionReputationMin": 10
      }
    }
    ,
    {
      "id": "quest-main-2045-red-dust-refugees",
      "name": "Беженцы красной пыли (2045)",
      "description": "Группа беженцев из красной зоны просит помощи. Им нужно добраться до безопасного района, но путь блокирован скавами и бандами. Нужно обеспечить безопасный проход.",
      "type": "main",
      "giverNpcId": "npc-marco-fix",
      "level": 5,
      "objectives": [
        { "id": "obj-accept", "description": "Принять задание у Марко", "type": "npc", "target": { "type": "npc", "id": "npc-marco-fix" }, "quantity": 1 },
        { "id": "obj-meet-refugees", "description": "Встретиться с беженцами (Santo Domingo)", "type": "location", "target": { "type": "location", "id": "loc-santo-domingo-001" }, "quantity": 1 },
        { "id": "obj-clear-path", "description": "Зачистить путь от угроз (5)", "type": "kill", "target": { "type": "enemy", "id": "npc-gangster-generic" }, "quantity": 5 },
        { "id": "obj-escort", "description": "Сопроводить беженцев в Watson", "type": "location", "target": { "type": "location", "id": "loc-watson-001" }, "quantity": 1 },
        { "id": "obj-return", "description": "Вернуться к Марко", "type": "npc", "target": { "type": "npc", "id": "npc-marco-fix" }, "quantity": 1 }
      ],
      "rewards": { "experience": 500, "money": 600, "items": ["item-components-basic"], "reputation": { "faction": "independent", "amount": 15 } },
      "requirements": { "level": 5, "reputation": null, "completedQuests": ["quest-main-2040-red-dawn"] },
      "metadata": {
        "skillChecks": [
          { "type": "cool", "dc": 15, "bonus": "negotiate-safe-passage", "description": "Договориться о безопасном проходе", "successEffects": { "reduceEnemies": 3, "xpBonus": 30 } },
          { "type": "medical", "dc": 13, "bonus": "treat-refugees", "description": "Оказать медицинскую помощь беженцам", "successEffects": { "xpBonus": 40, "reputation": { "faction": "independent", "amount": 5 } } },
          { "type": "tactics", "dc": 14, "bonus": "plan-route", "description": "Спланировать безопасный маршрут", "successEffects": { "reduceEnemies": 2, "timeReduction": 10 } }
        ],
        "epoch": "2030-2045",
        "theme": "red-dust-refugees"
      }
    }
    ,
    {
      "id": "quest-side-2052-corporate-espionage",
      "name": "Корпоративный шпионаж (2052)",
      "description": "Элизабет Чен просит помочь в корпоративном шпионаже. Нужно проникнуть в здание конкурента и украсть данные о новом проекте. Очень опасно.",
      "type": "side",
      "giverNpcId": "npc-elizabeth-chen",
      "level": 6,
      "objectives": [
        { "id": "obj-accept", "description": "Принять задание у Элизабет", "type": "npc", "target": { "type": "npc", "id": "npc-elizabeth-chen" }, "quantity": 1 },
        { "id": "obj-infiltrate", "description": "Проникнуть в корпоративное здание (Westbrook)", "type": "location", "target": { "type": "location", "id": "loc-westbrook-001" }, "quantity": 1 },
        { "id": "obj-steal-data", "description": "Украсть данные", "type": "item", "target": { "type": "item", "id": "item-corporate-data" }, "quantity": 1 },
        { "id": "obj-escape", "description": "Избежать преследования (4)", "type": "kill", "target": { "type": "enemy", "id": "npc-gangster-generic" }, "quantity": 4 },
        { "id": "obj-return", "description": "Вернуться к Элизабет", "type": "npc", "target": { "type": "npc", "id": "npc-elizabeth-chen" }, "quantity": 1 }
      ],
      "rewards": { "experience": 560, "money": 750, "items": [], "reputation": { "faction": "independent", "amount": 10 } },
      "requirements": { "level": 6, "reputation": null, "completedQuests": [] },
      "metadata": {
        "skillChecks": [
          { "type": "stealth", "dc": 16, "bonus": "silent-infiltration", "description": "Проникнуть незаметно", "successEffects": { "reduceEnemies": 2, "xpBonus": 40 } },
          { "type": "int", "dc": 15, "bonus": "hack-security", "description": "Взломать систему безопасности", "successEffects": { "reduceEnemies": 2, "itemBonus": "item-corporate-data" } },
          { "type": "cool", "dc": 16, "bonus": "bluff-guards", "description": "Обмануть охрану", "successEffects": { "reduceEnemies": 3, "xpBonus": 30 } }
        ],
        "highRisk": true,
        "stealthPreferred": true
      }
    }
    ,
    {
      "id": "quest-class-netrunner-2058-ai-fragment",
      "name": "Фрагмент ИИ (2058)",
      "description": "В сети обнаружен фрагмент старого ИИ, поврежденного DataKrash. NetWatch просит помочь извлечь его для анализа. Опасная операция в глубоких слоях сети.",
      "type": "side",
      "giverNpcId": "npc-elizabeth-chen",
      "level": 7,
      "objectives": [
        { "id": "obj-accept", "description": "Принять задание", "type": "npc", "target": { "type": "npc", "id": "npc-elizabeth-chen" }, "quantity": 1 },
        { "id": "obj-access-deep-net", "description": "Получить доступ к глубоким слоям сети", "type": "location", "target": { "type": "location", "id": "loc-downtown-001" }, "quantity": 1 },
        { "id": "obj-locate-ai", "description": "Найти фрагмент ИИ", "type": "item", "target": { "type": "item", "id": "item-ai-fragment" }, "quantity": 1 },
        { "id": "obj-extract", "description": "Извлечь фрагмент (противостоять защите)", "type": "kill", "target": { "type": "enemy", "id": "npc-ai-combat-proxy" }, "quantity": 2 },
        { "id": "obj-return", "description": "Вернуться к Элизабет", "type": "npc", "target": { "type": "npc", "id": "npc-elizabeth-chen" }, "quantity": 1 }
      ],
      "rewards": { "experience": 600, "money": 800, "items": ["item-ai-fragment"], "reputation": { "faction": "netwatch", "amount": 15 } },
      "requirements": { "level": 7, "reputation": null, "completedQuests": [] },
      "metadata": {
        "skillChecks": [
          { "type": "int", "dc": 17, "bonus": "track-ai-signature", "description": "Отследить сигнатуру ИИ", "successEffects": { "timeReduction": 15, "xpBonus": 50 } },
          { "type": "netrunning-combat", "dc": 16, "bonus": "defeat-ice", "description": "Победить ICE программы", "successEffects": { "reduceEnemies": 1, "xpBonus": 40 } },
          { "type": "cool", "dc": 17, "bonus": "resist-ai-influence", "description": "Сопротивляться влиянию ИИ", "successEffects": { "xpBonus": 50, "statusProtection": "cyberpsychosis" } }
        ],
        "classRequired": "netrunner",
        "netrunningRequired": true,
        "classBonus": { "xpMultiplier": 1.3, "reputationBonus": 1.5 }
      }
    }
    ,
    {
      "id": "quest-main-2072-independence-celebration",
      "name": "Празднование независимости (2072)",
      "description": "Найт-Сити празднует третью годовщину независимости от NUSA. Сара Миллер просит помочь обеспечить безопасность празднования. Нужно предотвратить теракты и конфликты.",
      "type": "main",
      "giverNpcId": "npc-sarah-miller",
      "level": 8,
      "objectives": [
        { "id": "obj-accept", "description": "Принять задание у Сары", "type": "npc", "target": { "type": "npc", "id": "npc-sarah-miller" }, "quantity": 1 },
        { "id": "obj-patrol", "description": "Патрулировать Downtown во время празднования", "type": "location", "target": { "type": "location", "id": "loc-downtown-001" }, "quantity": 1 },
        { "id": "obj-prevent-incident", "description": "Предотвратить инциденты (расследовать угрозы)", "type": "item", "target": { "type": "item", "id": "item-electronics-standard" }, "quantity": 2 },
        { "id": "obj-combat", "description": "Отразить атаки (4)", "type": "kill", "target": { "type": "enemy", "id": "npc-gangster-generic" }, "quantity": 4 },
        { "id": "obj-return", "description": "Вернуться к Саре", "type": "npc", "target": { "type": "npc", "id": "npc-sarah-miller" }, "quantity": 1 }
      ],
      "rewards": { "experience": 680, "money": 900, "items": [], "reputation": { "faction": "ncpd", "amount": 25 } },
      "requirements": { "level": 8, "reputation": null, "completedQuests": ["quest-main-2070-nusa-tensions"] },
      "metadata": {
        "skillChecks": [
          { "type": "perception", "dc": 16, "bonus": "detect-threats", "description": "Обнаружить угрозы заранее", "successEffects": { "reduceEnemies": 2, "xpBonus": 50 } },
          { "type": "cool", "dc": 16, "bonus": "de-escalate", "description": "Деэскалировать конфликт без боя", "successEffects": { "reduceEnemies": 2, "reputation": { "faction": "ncpd", "amount": 10 } } },
          { "type": "investigation", "dc": 15, "bonus": "find-plotters", "description": "Найти заговорщиков", "successEffects": { "xpBonus": 60, "reputation": { "faction": "ncpd", "amount": 15 } } }
        ],
        "epoch": "2060-2077",
        "theme": "independence"
      }
    }
    ,
    {
      "id": "quest-side-2078-relic-prototype",
      "name": "Прототип Реликта (2078)",
      "description": "Виктор Вектор слышал слухи о новом прототипе технологии Relic. Нужно найти источник информации и проверить, что это правда. Опасно — корпорации скрывают информацию.",
      "type": "side",
      "giverNpcId": "npc-victor-vector",
      "level": 9,
      "objectives": [
        { "id": "obj-accept", "description": "Принять задание у Виктора", "type": "npc", "target": { "type": "npc", "id": "npc-victor-vector" }, "quantity": 1 },
        { "id": "obj-investigate", "description": "Исследовать слухи (Westbrook)", "type": "location", "target": { "type": "location", "id": "loc-westbrook-001" }, "quantity": 1 },
        { "id": "obj-find-source", "description": "Найти источник информации", "type": "npc", "target": { "type": "npc", "id": "npc-elizabeth-chen" }, "quantity": 1 },
        { "id": "obj-steal-data", "description": "Украсть данные о прототипе", "type": "item", "target": { "type": "item", "id": "item-corporate-data" }, "quantity": 1 },
        { "id": "obj-combat", "description": "Избежать преследования (5)", "type": "kill", "target": { "type": "enemy", "id": "npc-gangster-generic" }, "quantity": 5 },
        { "id": "obj-return", "description": "Вернуться к Виктору", "type": "npc", "target": { "type": "npc", "id": "npc-victor-vector" }, "quantity": 1 }
      ],
      "rewards": { "experience": 720, "money": 950, "items": ["item-relic-data"], "reputation": { "faction": "independent", "amount": 12 } },
      "requirements": { "level": 9, "reputation": null, "completedQuests": [] },
      "metadata": {
        "skillChecks": [
          { "type": "investigation", "dc": 17, "bonus": "find-source-fast", "description": "Быстро найти источник", "successEffects": { "timeReduction": 20, "xpBonus": 40 } },
          { "type": "cool", "dc": 17, "bonus": "convince-source", "description": "Убедить источник дать информацию", "successEffects": { "reduceEnemies": 2, "xpBonus": 50 } },
          { "type": "stealth", "dc": 18, "bonus": "steal-undetected", "description": "Украсть данные незаметно", "successEffects": { "reduceEnemies": 3, "xpBonus": 60 } }
        ],
        "epoch": "2077-2093",
        "theme": "relic-prototype"
      }
    }
    ,
    {
      "id": "quest-faction-nomads-2082-badlands-route",
      "name": "Путь пустоши (2082)",
      "description": "Номады просят помочь прокладывать новый маршрут через пустошь. Нужно разведать местность, зачистить опасности и обеспечить безопасный проход для конвоя.",
      "type": "side",
      "giverNpcId": "npc-anna-petrova",
      "level": 9,
      "objectives": [
        { "id": "obj-accept", "description": "Принять задание", "type": "npc", "target": { "type": "npc", "id": "npc-anna-petrova" }, "quantity": 1 },
        { "id": "obj-scout", "description": "Разведать местность (Badlands)", "type": "location", "target": { "type": "location", "id": "loc-watson-001" }, "quantity": 1 },
        { "id": "obj-clear-threats", "description": "Зачистить угрозы (6)", "type": "kill", "target": { "type": "enemy", "id": "npc-gangster-generic" }, "quantity": 6 },
        { "id": "obj-escort-convoy", "description": "Сопроводить конвой", "type": "location", "target": { "type": "location", "id": "loc-downtown-001" }, "quantity": 1 },
        { "id": "obj-return", "description": "Вернуться к номадам", "type": "npc", "target": { "type": "npc", "id": "npc-anna-petrova" }, "quantity": 1 }
      ],
      "rewards": { "experience": 800, "money": 1100, "items": [], "reputation": { "faction": "nomads", "amount": 25 } },
      "requirements": { "level": 9, "reputation": { "faction": "nomads", "min": 15 }, "completedQuests": [] },
      "metadata": {
        "skillChecks": [
          { "type": "perception", "dc": 16, "bonus": "spot-ambushes", "description": "Обнаружить засады заранее", "successEffects": { "reduceEnemies": 2, "xpBonus": 50 } },
          { "type": "survival", "dc": 15, "bonus": "find-safe-route", "description": "Найти безопасный маршрут", "successEffects": { "reduceEnemies": 3, "timeReduction": 15 } },
          { "type": "driving", "dc": 14, "bonus": "lead-convoy", "description": "Эффективно вести конвой", "successEffects": { "xpBonus": 60, "reputation": { "faction": "nomads", "amount": 10 } } }
        ],
        "factionRequired": "nomads",
        "factionReputationMin": 15
      }
    }
    ,
    {
      "id": "quest-main-2085-blackwall-expansion",
      "name": "Расширение Blackwall (2085)",
      "description": "Элизабет Чен сообщает о планах расширения Blackwall. Нужно исследовать границы и собрать данные о новых секторах. Очень опасно — старые ИИ могут быть активны.",
      "type": "main",
      "giverNpcId": "npc-elizabeth-chen",
      "level": 10,
      "objectives": [
        { "id": "obj-accept", "description": "Принять задание у Элизабет", "type": "npc", "target": { "type": "npc", "id": "npc-elizabeth-chen" }, "quantity": 1 },
        { "id": "obj-access-blackwall", "description": "Получить доступ к границе Blackwall", "type": "location", "target": { "type": "location", "id": "loc-downtown-001" }, "quantity": 1 },
        { "id": "obj-map-sectors", "description": "Картографировать новые сектора (3)", "type": "item", "target": { "type": "item", "id": "item-blackwall-data" }, "quantity": 3 },
        { "id": "obj-combat-ai", "description": "Противостоять враждебным ИИ (5)", "type": "kill", "target": { "type": "enemy", "id": "npc-ai-combat-proxy" }, "quantity": 5 },
        { "id": "obj-return", "description": "Вернуться к Элизабет", "type": "npc", "target": { "type": "npc", "id": "npc-elizabeth-chen" }, "quantity": 1 }
      ],
      "rewards": { "experience": 1000, "money": 1400, "items": ["item-blackwall-data"], "reputation": { "faction": "netwatch", "amount": 20 } },
      "requirements": { "level": 10, "reputation": null, "completedQuests": ["quest-main-2080-corporate-shadow"] },
      "metadata": {
        "skillChecks": [
          { "type": "int", "dc": 18, "bonus": "navigate-blackwall", "description": "Навигация по границе Blackwall", "successEffects": { "timeReduction": 20, "xpBonus": 100 } },
          { "type": "netrunning-combat", "dc": 19, "bonus": "defeat-rogue-ai", "description": "Победить враждебных ИИ", "successEffects": { "reduceEnemies": 2, "xpBonus": 150 } },
          { "type": "cool", "dc": 18, "bonus": "resist-cyberpsychosis", "description": "Сопротивляться киберпсихозу", "successEffects": { "statusProtection": "cyberpsychosis", "xpBonus": 80 } }
        ],
        "netrunningRequired": true,
        "highRisk": true,
        "epoch": "2077-2093",
        "theme": "blackwall"
      }
    }
    ,
    {
      "id": "quest-side-2088-corpo-war-zone",
      "name": "Зона корпоративной войны (2088)",
      "description": "Arasaka и Militech ведут открытую войну в Downtown. Марко просит помочь эвакуировать гражданских из зоны конфликта. Крайне опасно.",
      "type": "side",
      "giverNpcId": "npc-marco-fix",
      "level": 10,
      "objectives": [
        { "id": "obj-accept", "description": "Принять задание у Марко", "type": "npc", "target": { "type": "npc", "id": "npc-marco-fix" }, "quantity": 1 },
        { "id": "obj-enter-warzone", "description": "Войти в зону боевых действий (Downtown)", "type": "location", "target": { "type": "location", "id": "loc-downtown-001" }, "quantity": 1 },
        { "id": "obj-find-civilians", "description": "Найти гражданских (5)", "type": "npc", "target": { "type": "npc", "id": "npc-gangster-generic" }, "quantity": 1 },
        { "id": "obj-evacuate", "description": "Эвакуировать гражданских", "type": "location", "target": { "type": "location", "id": "loc-watson-001" }, "quantity": 1 },
        { "id": "obj-combat", "description": "Отразить атаки (8)", "type": "kill", "target": { "type": "enemy", "id": "npc-gangster-generic" }, "quantity": 8 },
        { "id": "obj-return", "description": "Вернуться к Марко", "type": "npc", "target": { "type": "npc", "id": "npc-marco-fix" }, "quantity": 1 }
      ],
      "rewards": { "experience": 900, "money": 1300, "items": [], "reputation": { "faction": "independent", "amount": 35 } },
      "requirements": { "level": 10, "reputation": null, "completedQuests": [] },
      "metadata": {
        "skillChecks": [
          { "type": "stealth", "dc": 18, "bonus": "avoid-detection", "description": "Избежать обнаружения", "successEffects": { "reduceEnemies": 4, "xpBonus": 100 } },
          { "type": "tactics", "dc": 17, "bonus": "coordinate-evacuation", "description": "Координировать эвакуацию", "successEffects": { "reduceEnemies": 3, "xpBonus": 80 } },
          { "type": "medical", "dc": 16, "bonus": "treat-civilians", "description": "Оказать помощь гражданским", "successEffects": { "xpBonus": 100, "reputation": { "faction": "independent", "amount": 15 } } }
        ],
        "highRisk": true,
        "extremeDanger": true,
        "epoch": "2077-2093"
      }
    }
    ,
    {
      "id": "quest-class-solo-2091-paramount-security",
      "name": "Безопасность Параметрики (2091)",
      "description": "Сара Миллер нанимает соло для обеспечения безопасности параметрических ярмарок. Нужно предотвратить теракты и защитить важных персон. Высокий уровень сложности.",
      "type": "side",
      "giverNpcId": "npc-sarah-miller",
      "level": 11,
      "objectives": [
        { "id": "obj-accept", "description": "Принять задание у Сары", "type": "npc", "target": { "type": "npc", "id": "npc-sarah-miller" }, "quantity": 1 },
        { "id": "obj-secure-venue", "description": "Обеспечить безопасность места (Downtown)", "type": "location", "target": { "type": "location", "id": "loc-downtown-001" }, "quantity": 1 },
        { "id": "obj-prevent-threats", "description": "Предотвратить угрозы (расследовать)", "type": "item", "target": { "type": "item", "id": "item-electronics-standard" }, "quantity": 3 },
        { "id": "obj-combat", "description": "Отразить атаки (10)", "type": "kill", "target": { "type": "enemy", "id": "npc-gangster-generic" }, "quantity": 10 },
        { "id": "obj-protect-vip", "description": "Защитить важных персон", "type": "npc", "target": { "type": "npc", "id": "npc-elizabeth-chen" }, "quantity": 1 },
        { "id": "obj-return", "description": "Вернуться к Саре", "type": "npc", "target": { "type": "npc", "id": "npc-sarah-miller" }, "quantity": 1 }
      ],
      "rewards": { "experience": 1200, "money": 1600, "items": ["item-components-basic"], "reputation": { "faction": "ncpd", "amount": 30 } },
      "requirements": { "level": 11, "reputation": null, "completedQuests": [] },
      "metadata": {
        "skillChecks": [
          { "type": "perception", "dc": 19, "bonus": "detect-threats-early", "description": "Обнаружить угрозы заранее", "successEffects": { "reduceEnemies": 5, "xpBonus": 150 } },
          { "type": "tactics", "dc": 18, "bonus": "coordinate-security", "description": "Координировать безопасность", "successEffects": { "reduceEnemies": 4, "xpBonus": 120 } },
          { "type": "intimidation", "dc": 17, "bonus": "deter-attackers", "description": "Устрашить нападающих", "successEffects": { "reduceEnemies": 3, "reputation": { "faction": "ncpd", "amount": 15 } } }
        ],
        "classRequired": "solo",
        "classBonus": { "xpMultiplier": 1.3, "reputationBonus": 1.5 },
        "epoch": "2077-2093",
        "theme": "paramount-security"
      }
    }
    ,
    {
      "id": "quest-main-2093-simulation-reveal",
      "name": "Раскрытие симуляции (2093)",
      "description": "Виктор Вектор и Элизабет Чен объединяют усилия. Данные о симуляции накапливаются. Нужно проникнуть в самое сердце системы и раскрыть истину. Финальный квест эпохи.",
      "type": "main",
      "giverNpcId": "npc-victor-vector",
      "level": 12,
      "objectives": [
        { "id": "obj-accept", "description": "Принять задание", "type": "npc", "target": { "type": "npc", "id": "npc-victor-vector" }, "quantity": 1 },
        { "id": "obj-gather-evidence", "description": "Собрать все доказательства симуляции (5)", "type": "item", "target": { "type": "item", "id": "item-simulation-evidence" }, "quantity": 5 },
        { "id": "obj-access-core", "description": "Получить доступ к ядру системы", "type": "location", "target": { "type": "location", "id": "loc-downtown-001" }, "quantity": 1 },
        { "id": "obj-combat-guardians", "description": "Противостоять защитникам системы (10)", "type": "kill", "target": { "type": "enemy", "id": "npc-gangster-generic" }, "quantity": 10 },
        { "id": "obj-reveal-truth", "description": "Раскрыть истину", "type": "item", "target": { "type": "item", "id": "item-simulation-core" }, "quantity": 1 },
        { "id": "obj-return", "description": "Вернуться к Виктору и Элизабет", "type": "npc", "target": { "type": "npc", "id": "npc-victor-vector" }, "quantity": 1 }
      ],
      "rewards": { "experience": 1500, "money": 2000, "items": ["item-simulation-core"], "reputation": { "faction": "independent", "amount": 50 } },
      "requirements": { "level": 12, "reputation": null, "completedQuests": ["quest-main-2090-simulation-whispers", "quest-main-2093-net-shift"] },
      "metadata": {
        "skillChecks": [
          { "type": "int", "dc": 20, "bonus": "understand-simulation", "description": "Понять природу симуляции", "successEffects": { "xpBonus": 200, "itemBonus": "item-simulation-core" } },
          { "type": "cool", "dc": 19, "bonus": "resist-madness", "description": "Сопротивляться безумию от истины", "successEffects": { "statusProtection": "insanity", "xpBonus": 150 } },
          { "type": "netrunning-combat", "dc": 20, "bonus": "defeat-system-guardians", "description": "Победить защитников системы", "successEffects": { "reduceEnemies": 5, "xpBonus": 300 } }
        ],
        "finalQuest": true,
        "epoch": "2077-2093",
        "theme": "simulation-reveal",
        "storyImpact": "maximum"
      }
    }
  ]
}

